matrixprofile/__init__.py
matrixprofile/discords.py
matrixprofile/distanceProfile.py
matrixprofile/fluss.py
matrixprofile/matrixProfile.py
matrixprofile/motifs.py
matrixprofile/order.py
matrixprofile/regimes.py
matrixprofile/scrimp.py
matrixprofile/utils.py
matrixprofile_ts-0.0.9.dist-info/LICENSE
matrixprofile_ts-0.0.9.dist-info/METADATA
matrixprofile_ts-0.0.9.dist-info/WHEEL
matrixprofile_ts-0.0.9.dist-info/top_level.txt
matrixprofile_ts-0.0.9.dist-info/RECORD
