Metadata-Version: 2.1
Name: matrixprofile-ts
Version: 0.0.9
Summary: An Open Source Python Time Series Library For Motif Discovery using Matrix Profile
Home-page: https://github.com/target/matrixprofile-ts
Author: Andrew Van Benschoten
Author-email: avbs89@gmail.com
License: UNKNOWN
Platform: UNKNOWN
Classifier: Programming Language :: Python :: 2
Classifier: Programming Language :: Python :: 3
Classifier: License :: OSI Approved :: Apache Software License
Classifier: Operating System :: OS Independent
Requires-Dist: numpy (>=1.11.3)
